zentropy/__init__.py
zentropy/cli.py
zentropy/client.py
zentropy/connection.py
zentropy/exceptions.py
zentropy_py-0.1.4.dist-info/METADATA
zentropy_py-0.1.4.dist-info/WHEEL
zentropy_py-0.1.4.dist-info/entry_points.txt
zentropy_py-0.1.4.dist-info/RECORD
